rolly/__init__.py
rolly/char.py
rolly/cli.py
rolly/output.py
rolly/py.typed
rolly/roll.py
rolly/roll_test.py
rolly/themes.py
rolly/themes_test.py
rolly-1.0.1.dist-info/WHEEL
rolly-1.0.1.dist-info/entry_points.txt
rolly-1.0.1.dist-info/METADATA
rolly-1.0.1.dist-info/RECORD
