Metadata-Version: 2.3
Name: rolly
Version: 1.0.1
Summary: Roll dice on the command line because why not?
Author: George Lesica
Author-email: George Lesica <george@lesica.com>
Requires-Dist: click>=8.3.0
Requires-Python: >=3.14
